hx_testpackage36-0.2.dist-info/DESCRIPTION.rst
hx_testpackage36-0.2.dist-info/METADATA
hx_testpackage36-0.2.dist-info/RECORD
hx_testpackage36-0.2.dist-info/WHEEL
hx_testpackage36-0.2.dist-info/metadata.json
hx_testpackage36-0.2.dist-info/top_level.txt
test_package/__init__.py
