Metadata-Version: 2.0
Name: hx-testpackage36
Version: 0.2
Summary: Testing the efficientcy of Inspector
Home-page: UNKNOWN
Author: Tector Pro
License: UNKNOWN
Platform: UNKNOWN
Requires-Python: >3.0
Requires-Dist: hx-testpackage27
